subbrute/__init__.py
subbrute/core.py
subbrute-2.0.0.dist-info/METADATA
subbrute-2.0.0.dist-info/WHEEL
subbrute-2.0.0.dist-info/top_level.txt
subbrute-2.0.0.dist-info/RECORD
