Metadata-Version: 2.1
Name: subbrute
Version: 2.0.0
Summary: A lightweight subdomain brute-forcing tool with live updates via callback.
Home-page: https://github.com/ByteBreach/subbrute
Author: MrFidal
Author-email: mrfidal@proton.me
Classifier: Programming Language :: Python :: 3
Classifier: License :: OSI Approved :: MIT License
Classifier: Operating System :: OS Independent
Requires-Python: >=3.6
